LICENSE
MANIFEST.in
README.md
requirements.txt
setup.cfg
setup.py
pippin/__init__.py
pippin/config.py
pippin/main.py
pippin/pippin_cli.py
pippin/sample.config.yaml
pippin/version.py
pippin/db/__init__.py
pippin/db/redis.py
pippin/db/tortoise_config.py
pippin/db/models/__init__.py
pippin/db/models/account.py
pippin/db/models/adhoc_account.py
pippin/db/models/block.py
pippin/db/models/wallet.py
pippin/model/__init__.py
pippin/model/difficulty.py
pippin/model/secrets.py
pippin/network/__init__.py
pippin/network/nano_websocket.py
pippin/network/rpc_client.py
pippin/network/work_client.py
pippin/server/__init__.py
pippin/server/pippin_server.py
pippin/util/__init__.py
pippin/util/crypt.py
pippin/util/nano_util.py
pippin/util/random.py
pippin/util/utils.py
pippin/util/validators.py
pippin/util/wallet.py
pippin_wallet.egg-info/PKG-INFO
pippin_wallet.egg-info/SOURCES.txt
pippin_wallet.egg-info/dependency_links.txt
pippin_wallet.egg-info/entry_points.txt
pippin_wallet.egg-info/requires.txt
pippin_wallet.egg-info/top_level.txt
pippin_wallet.egg-info/zip-safe