Metadata-Version: 2.1
Name: pippin-wallet
Version: 2.1.2
Summary: A production-ready, high-performance developer wallet for Nano and BANANO.
Home-page: https://github.com/appditto/pippin_nano_wallet
Author: Appditto LLC
Author-email: hello@appditto.com
License: MIT License
Keywords: cryptocurrency wallet nano banano bitcoin api aiohttp async asyncio aio
Classifier: License :: OSI Approved :: MIT License
Classifier: Development Status :: 5 - Production/Stable
Classifier: Intended Audience :: Developers
Classifier: Programming Language :: Python :: 3
Classifier: Programming Language :: Python :: 3.6
Classifier: Programming Language :: Python :: 3.7
Classifier: Programming Language :: Python :: 3.8
Classifier: Framework :: AsyncIO
Classifier: Topic :: Security :: Cryptography
Classifier: Operating System :: POSIX
Classifier: Operating System :: MacOS :: MacOS X
License-File: LICENSE
